LICENSE.rst
MANIFEST.in
README.rst
setup.cfg
setup.py
anodi/__init__.py
anodi/tools.py
anodi.egg-info/PKG-INFO
anodi.egg-info/SOURCES.txt
anodi.egg-info/dependency_links.txt
anodi.egg-info/namespace_packages.txt
anodi.egg-info/requires.txt
anodi.egg-info/top_level.txt