Metadata-Version: 1.1
Name: anodi
Version: 0.0.2
Summary: A decorator-based backport of PEP-3107 function annotations to Python 2.7, and related tools.
Home-page: https://github.com/agoraplex/anodi
Author: Tripp Lilley
Author-email: tripplilley@gmail.com
License: BSD
Platform: UNKNOWN
Classifier: Development Status :: 3 - Alpha
Classifier: Intended Audience :: Developers
Classifier: Operating System :: OS Independent
Classifier: Programming Language :: Python :: 2.7
Classifier: Topic :: Documentation
Classifier: Topic :: Software Development :: Documentation
Classifier: Topic :: Software Development :: Libraries :: Python Modules
